{"n":"Nevit Family Stew","lv":20,"maps":["1879451216","1879451222"],"steps":[{"i":1,"pts":[[-4.645957,-122.351265,"1879451216"],[-4.583213,-122.24611,"1879451216"],[-4.57706,-122.201035,"1879451216"],[-4.6518455,-122.29899,"1879451216"]],"t":"Rhiangar Nevit has asked you gather supplies for her family's favourite stew. Ruddy-coat goats can be found west of Herne, and the rest of the ingredi…"},{"i":2,"pts":[[5.153701,-121.9998,"1879451222"]],"t":"Rhiangar is in the Mayor's house, in Herne. You should being the ingredients for dinner to Rhiangar."}]}