{"n":"Instance: Passage of the Marshes","lv":100,"maps":[],"steps":[{"i":1,"pts":[[-16.60413,-27.297411]],"t":"Frodo has slowed his pace. The Dead Marshes are taking their toll on him."},{"i":2,"pts":[[-16.576494,-27.263378]],"t":"Gollum has bounded back to you. Your master is right: the creature has not guided you wrong... yet. You still do not trust him."},{"i":4,"pts":[[-16.60413,-27.297411]],"t":"Frodo looks very tired. The journey through the swamp is taking its toll."},{"i":6,"pts":[[-13.484892,-26.65788]],"t":"The journey through the swamp has proven to be very difficult, with no end in sight."},{"i":8,"pts":[[-13.540205,-26.698359]],"t":"Frodo has wandered off by himself! You have to find him!"},{"i":9,"pts":[[-13.431699,-26.852987]],"t":"Frodo has decided to catch some sleep, and wants you to sit next to him."},{"i":11,"pts":[[-13.429677,-26.864746]],"t":"You do not like what you overheard Gollum muttering to himself, if you did not imagine it."},{"i":12,"pts":[[-13.540205,-26.698359]],"t":"You hate to do it, but it is time to wake Frodo and set out once again."},{"i":15,"pts":[[-12.012031,-26.876972]],"t":"Gollum is terrified, and is in no shape to go on. The frightening encounter with the terrible shadow has shaken him tremendously."},{"i":16,"pts":[[-11.935195,-26.740107]],"t":"How has Frodo fared?"}]}