{"n":"Emyn Ernil Cave - Shaky Scaffolds","lv":100,"maps":["1879310195"],"steps":[{"i":1,"pts":[[56.038864,45.874317],[56.15486,45.434803],[56.180134,45.58379],[55.926777,45.62537],[55.968124,45.712635]],"t":"Rotting scaffolding may be found in the large cave beneath Emyn Ernil. Lhossil asked you to venture beneath Emyn Ernil and repair some of the scaffold…"},{"i":2,"pts":[[-71.20317,-75.24805,"1879310195"]],"t":"Lhossil can be found in Dol Amroth. Lhossil will be pleased to hear the scaffold has been shored up."}]}