{"n":"A Creeping Sensation","lv":130,"maps":[],"steps":[{"i":1,"pts":[[-133.35802,63.259747]],"t":"Mekhnet has been keeping an eye on the opposite shoreline to the east of the the Kambráda encampment in Amdân. You should check to see if anything str…"},{"i":2,"pts":[[-133.35449,63.264236]],"t":"You have found nothing of note other than an inert sapper-bomb. Perhaps inspecting it will unlock more clues.","kz":{"c":1}},{"i":3,"pts":[[-134.25902,63.396034]],"t":"Mekhnet waits near the Kambráda encampment in the eastern part of Amdân. She will want to hear about the goblin-sapper and the bomb you found."}]}