{"n":"An Angler's Advice","lv":150,"maps":[],"steps":[{"i":1,"pts":[[-78.81744,-15.5453415]],"t":"The first fishing spot is on a bridge crossing a stream east of Arwáth. You should go there and try catching a fish."},{"i":3,"pts":[[-81.66221,-18.383652]],"t":"The second fishing spot is south along the same stream as the first. You should go there and try catching a fish."},{"i":5,"pts":[[-71.934135,-30.499199]],"t":"The third fishing spot is a dock on the Ikorbân, far to the south-east past the Wrackwade. You should go there and try catching a fish."},{"i":7,"pts":[[-81.02276,-22.890898]],"t":"You caught a fish at each of the three locations Zildug recommended. You should return to Iridír and show your catch to the fisherman."}]}