{"n":"The Crumbling Halls of Glynafon","lv":40,"maps":["1879443714"],"steps":[{"i":1,"pts":[[-19.217861,-40.565674]],"t":"The abandoned burrows of Glynafon are in the eastern Angle. You should explore the abandoned burrows and bring anything of interest back to Cedivor."},{"i":2,"pts":[[-18.414648,-39.60493,"1879443714"]],"t":"Cedivor Hedgerow is outside of Glynafon, in the eastern Angle. You should bring the stone to Cedivor."},{"i":3,"pts":[[-22.143036,-34.712765,"1879443714"]],"t":"Narnien is located in Gaerond, in the northern Angle. You should tell Narnien that you have found a strange artifact."}]}