{"n":"Food for the Riders","lv":102,"maps":[],"steps":[{"i":1,"pts":[[-28.095604,-46.098812]],"t":"The cauldron can be found in the War-stead of the Helmingas. You should collect porridge from the cauldron."},{"i":2,"pts":[[-27.754639,-45.957645],[-27.800068,-45.67278],[-28.047987,-45.84194],[-28.02376,-45.691048],[-28.138515,-45.297077],[-27.621962,-45.479385],[-27.634794,-45.228107],[-27.659912,-45.208138]],"t":"Hungry Rohirrim can be found in the War-steads of the Helmingas and the King's Men. You should feed the hungry riders."}]}