{"n":"Instance: Vengeance of the Fallen","lv":105,"maps":[],"steps":[{"i":1,"pts":[[-6.859951,-31.401327],[-7.363271,-30.731562]],"t":"Faramir is just outside Ondoher's Folly in Dagorlad. You should speak to Faramir when you are ready to assault Ondoher's Folly and confront the Bloodl…"},{"i":8,"pts":[[-6.859951,-31.401327],[-7.363271,-30.731562]],"t":"Faramir can be found at Ondoher's Folly. Burudagath has been defeated and Faramir has reappeared within the Fane of Screaming at Ondoher's Folly."}]}