{"n":"Chapter 3.1: A Matter of Survival","lv":130,"maps":[],"steps":[{"i":1,"pts":[[-56.18717,21.097725]],"t":"Runerik Knotbeard is outside his lodge in the village of Limlók."},{"i":2,"pts":[[-55.89591,20.943935]],"t":"The box of scrolls is near the task board in Limlók."},{"i":3,"pts":[[-56.079266,20.875225]],"t":"Glóin is in the centre of the village, preparing his ravens to carry messages to Skarháld and the Lonely Mountain."},{"i":4,"pts":[[-56.086082,20.873016]],"t":"Glóin is in the centre of the village, preparing his ravens to carry messages to Skarháld and the Lonely Mountain."},{"i":5,"pts":[[-56.0716,20.876621]],"t":"A young Beorning child stands nearby, fascinated by Glóin and the messenger-ravens."},{"i":6,"pts":[[-55.835274,20.786865]],"t":"Yrsa Spearwife is in south-east Limlók. According to her son Vídar, Yrsa has tasked him with scouting outside the village once a week."},{"i":7,"pts":[[-57.269512,17.44082],[-55.78865,18.146864],[-54.426727,19.445215]],"t":"Yrsa told you to scout the wild lands south of Limlók with her son Vídar. You will find the Beorning boy at one of three different spots: to the south…"},{"i":8,"pts":[[-55.835274,20.786865]],"t":"Yrsa Spearwife is in south-east Limlók."},{"i":9,"pts":[[-56.244324,21.219687]],"t":"The dwarves have gathered behind Runerik and Yrsa's lodge to release the messenger-ravens."},{"i":10,"pts":[[-56.208855,21.195936]],"t":"Imák is behind Runerik's lodge to watch the release of the messenger-ravens."},{"i":12,"pts":[[-56.18717,21.097725]],"t":"Runerik Knotbeard is outside his lodge in the village of Limlók."}]}