{"n":"Lore-master: Friend of Turtles","lv":29,"maps":["1879084151"],"steps":[{"i":1,"pts":[[-27.149374,-31.92879,"1879084151"]],"t":"The turtle can be found hiding among fallen stones just to the east of the Circle of Blood. Radagast has asked you to coax the turtle to safety, teach…"},{"i":2,"pts":[[-27.666279,-30.047186]],"t":"Radagast the Brown is at Barad Dhorn in Agamaur. Radagast has asked you to coax a turtle to safety, teaching you the importance of the bond with the g…"},{"i":3,"pts":[[-27.664804,-30.047567]],"t":"Radagast the Brown is at Barad Dhorn. You should find out if Radagast the Brown has anything else for you to do."}]}