{"n":"Paralyzed by Grief","lv":85,"maps":["1879265611"],"steps":[{"i":1,"pts":[[50.75291,-118.98134]],"t":"The wood for the Mead-hall fire pits are kept along the wall to Reeve Gárwig's left. Gárwig has requested a log be put on the fire. It seems to be har…"},{"i":2,"pts":[[50.72123,-118.92886]],"t":"Gárwig asked for the log be put on the fire-pit to his left. Gárwig has requested a log be put on the fire. It seems to be harder and harder to keep t…"},{"i":3,"pts":[[50.698513,-118.91246]],"t":"Gárwig awaits his fate on the throne in the Mead-hall."},{"i":4,"pts":[[-60.84122,-39.4638,"1879265611"]],"t":"The messenger which Gárwig asked you to send to Dunfast is waiting near the stables in Forlaw."},{"i":5,"pts":[[50.705994,-118.91829],[50.706074,-118.91746]],"t":"Cyneberg is keeping Gárwig company in Lornsettle, the Mead-hall of Forlaw."}]}