{"n":"Finding Blue","lv":142,"maps":[],"steps":[{"i":1,"pts":[[-68.55583,-58.848522],[-68.74615,-58.536728],[-68.72402,-58.292507],[-68.85361,-58.114475],[-69.034134,-58.128784],[-69.112175,-58.504753],[-68.83085,-58.725044],[-68.9695,-58.287273]],"t":"Traps can be found outside the hamlet of Alagrant, in the Blackroot Vale. Dírion has asked you to search the traps outside Alagrant for any sign of 'B…"},{"i":2,"pts":[[-68.96993,-58.285862]],"t":"The sprung trap can be found outside Alagrant, in the Blackroot Vale. You have found a small blue object caught in one the traps. You should free 'Blu…"},{"i":3,"pts":[[-68.468796,-58.625107]],"t":"Draug can be found in Alagrant, in the Blackroot Vale. You have found 'Blue' in one of the traps outside Alagrant. You should return 'Blue' to Draug i…"},{"i":4,"pts":[[-68.46104,-58.63914]],"t":"Dírion can be found in Alagrant, in the Blackroot Vale. You have returned 'Blue' to Draug and he appears pleased. You should talk to Dírion."}]}