{"n":"Ronglagam: Stone Nests","lv":132,"maps":[],"steps":[{"i":1,"pts":[[-115.238045,-46.674213]],"t":"Stone-claw burrows can be found at Ronglagam in Máttugard. You should destroy the stone-claw burrows."},{"i":2,"pts":[[-115.24248,-46.864853],[-115.40646,-46.55893],[-115.42091,-46.78221],[-115.25597,-46.688545],[-115.44862,-46.691235],[-115.28761,-46.507866],[-115.22594,-46.50989],[-115.23926,-46.592365],[-115.03641,-46.497505],[-115.16558,-46.592915]],"t":"Stone-claw burrows can be found at Ronglagam in Máttugard. You should destroy the stone-claw burrows."}]}