{"n":"Bustle in the Blue Theatre","lv":100,"maps":["1879330360"],"steps":[{"i":1,"pts":[[-19.708897,-66.57993,"1879330360"],[-19.772627,-66.550804,"1879330360"]],"t":"The Blue Theatre can be found to the south in the Fourth Circle of Minas Tirith. Polla has asked you to meet her and the rest of the Cloudyheads in th…"},{"i":2,"pts":[[56.379646,25.819736],[56.72695,26.128105]],"t":"Members of the Cloudyheads can be found inside the Blue Theatre in the Fourth Circle of Minas Tirith. You have arrived at the Blue Theatre and should …"},{"i":4,"pts":[[56.710194,26.12745]],"t":"Polla Stoutley and the Cloudyheads can be found inside the Blue Theatre to the far right of the entrance in an alcove with a fire-place. You have help…"}]}