{"n":"Chapter 14.5: A Final Escape","lv":128,"maps":["1879393474"],"steps":[{"i":1,"pts":[[56.387966,11.594121]],"t":"Gothmog is in the throne room of Barad Cúron, trying to speak despite his wounds."},{"i":2,"pts":[[56.379745,11.61002]],"t":"The shade of Isildur is in the throne room of Barad Cúron."},{"i":3,"pts":[[56.406933,11.592334]],"t":"The shade of Isildur has asked you to bring the casket containing the dust of his bones out of Barad Cúron."},{"i":4,"pts":[[1.7403222,-67.46833]],"t":"Ayorzén is waiting for you on the uppermost tier of Minas Morgul."},{"i":5,"pts":[[4.154834,-65.06817,"1879393474"]],"t":"You did not find Ayorzén at the meeting-place, and should look for him at Echad Uial."},{"i":6,"pts":[[4.172695,-65.06313,"1879393474"]],"t":"Mithrandir is at Echad Uial."},{"i":7,"pts":[[4.1717186,-65.07458,"1879393474"]],"t":"Prince Faramir is at Echad Uial."},{"i":8,"pts":[[4.172695,-65.06313,"1879393474"],[56.406933,11.592334]],"t":"Mithrandir is at Echad Uial."}]}