{"n":"Sagroth: Attention to Detail","lv":140,"maps":["1879453499"],"steps":[{"i":1,"pts":[[49.034336,76.39601]],"t":"Use the Instance Finder to enter 'Sagroth, Lair of Vermin' on any difficulty."},{"i":2,"pts":[[48.33164,77.6701],[48.62117,77.558334],[48.687794,77.1217],[48.66748,76.88682],[48.752987,76.66176],[48.924587,76.44017],[48.36037,76.895035]],"t":"Piles of unidentifiable filth can be found in 'Sagroth, Lair of Vermin.' You should destroy them."},{"i":3,"pts":[[-28.138895,70.21463,"1879453499"]],"t":"Lágsaith has recounted, in excruciating detail, the disgusting filth she and her comrades encountered while in the sewers. You should tell Avlath in B…"}]}