{"n":"The Bridges of Glyn Helyg","lv":10,"maps":[],"steps":[{"i":1,"pts":[[-25.841787,-62.477455],[-25.657118,-62.88018],[-25.924795,-62.73944],[-25.745321,-63.01254],[-25.90626,-62.525883],[-25.937353,-62.56129]],"t":"Ponta Gochelgar has asked you to examine the bridges of Glyn Helyg for signs of rot and wear. The bridges span the gaps along the cliffs of Glyn Helyg…"},{"i":2,"pts":[[-26.024931,-62.51399]],"t":"You should report back to Ponta about the state of the bridges. Ponta Gochelgar is in Glyn Helyg."}]}