{"n":"Instance: A Silent Presence","lv":136,"maps":["1879427492"],"steps":[{"i":1,"pts":[[-69.888794,52.27916,"1879427492"],[-69.88064,52.278065,"1879427492"]],"t":"Imák and Venko wait for you on the hill upon which the Drearspire stands."},{"i":3,"pts":[[-69.87746,52.269512,"1879427492"],[-69.8717,52.26863,"1879427492"]],"t":"Venko stands before a side entrance to the Drearspire, considering its suitability for your purpose."},{"i":4,"pts":[[48.702637,63.01652]],"t":"You have entered the Drearspire with Imák and Venko, in search of answers: what villainy have the Angmarim conducted within Câr Bronach?"},{"i":5,"pts":[[48.658104,63.0109],[48.658516,63.01621]],"t":"You have entered the Drearspire with Imák and Venko, in search of answers: what villainy have the Angmarim conducted within Câr Bronach?"},{"i":7,"pts":[[48.657616,63.025154]],"t":"Inside the Drearspire, Venko has called for you to halt."}]}