{"n":"The Source of the Mist","lv":83,"maps":[],"steps":[{"i":1,"pts":[[-76.81207,-38.572197],[-76.846634,-38.297245]],"t":"The source of the mist can likely be found to the west of Oldheart. You should search for the source to the ugly-looking mist that hangs above the tre…"},{"i":2,"pts":[[-76.964806,-38.425644],[-76.89942,-38.163807],[-76.964325,-38.60372],[-76.827446,-38.184834],[-76.95972,-38.49048],[-76.95934,-38.65135],[-76.99591,-38.340633],[-76.7131,-38.289413],[-76.73395,-38.374275]],"t":"The Orcs and Uruks passing through this area have left filth all around the edges of this poor little pond. You should investigate what manner of filt…"},{"i":3,"pts":[[-76.86178,-38.57159]],"t":"You suspect that the little bird sought by Oldheart inhaled the fumes of this foetid pond, and likely died of the poisons. You should search for the l…"}]}