{"n":"Book 4, Chapter 5: Hiding in the Dark","lv":38,"maps":["1879048291","1879048293","1879048294"],"steps":[{"i":1,"pts":[[-20.692558,-29.729393,"1879048293"],[-14.530751,-32.631104],[-18.326288,-30.80952,"1879048294"],[-20.424404,-30.446415,"1879048293"],[-19.112402,-30.527548,"1879048294"],[-13.905518,-32.289402]],"t":"Elladan gave you his notes containing the locations of the troll-caves. Elladan wants you to search three troll-caves with Glorfindel's beryl. &lt;rgb…"},{"i":2,"pts":[[-15.175156,-31.650175,"1879048291"]],"t":"Elladan is at Thorenhad, his camp among the Bruinen Gorges, north of the bear-dens. Elladan is waiting to hear what Glorfindel's beryl revealed: that …"}]}