{"n":"Hospitality in a Strange Land","lv":71,"maps":["1879228527"],"steps":[{"i":1,"pts":[[-62.995037,-26.185225,"1879228527"]],"t":"Cynred, the keeper of the food and keys, is near the lock-houses of Stangard in Eorlsmead. You should speak with Cynred at Sabert's recommendation tha…"},{"i":2,"pts":[[-63.84867,-26.3416,"1879228527"],[53.04414,19.538925]],"t":"The Mead Hall is the large structure at the top of Stangard's hill. You should seek entrance to the Mead Hall by speaking with Gadda, the guard."},{"i":3,"pts":[[53.05279,19.564804],[53.055546,19.569715]],"t":"Stanric, the leader of Stangard, can be found in the Mead Hall. You should seek hospitality in Stangard from Stanric."},{"i":4,"pts":[[53.041286,19.564344],[53.036404,19.570038]],"t":"Sithric stands at the head of the Mead Hall in Stangard. You should speak with Sithric."}]}