{"n":"Dwindling Hope","lv":62,"maps":["1879157648"],"steps":[{"i":1,"pts":[[-54.718044,-11.530175,"1879157648"],[-55.179638,-11.561006,"1879157648"],[-54.726032,-12.355527,"1879157648"]],"t":"The missing Malledhrim scouts can surely be found in Dannenglor, north of the Haunted Inn. You should search Dannenglor for the missing Elves, though …"},{"i":2,"pts":[[-56.69955,-14.003652]],"t":"Fernachar is in the Haunted Inn in the Dourstocks, south of Dannenglor. You should speak with Fernachar and tell him that the three scouts met their d…"}]}