{"n":"Instance: Ruins of the Ancestors","lv":130,"maps":[],"steps":[{"i":1,"pts":[[-132.99486,64.542946]],"t":"Gori waits for you by the side of the River Kibil-nâla."},{"i":2,"pts":[[-132.99486,64.542946]],"t":"Gori continues his way through the ruins, too distracted to notice any imminent danger."},{"i":3,"pts":[[-132.99486,64.542946]],"t":"Gori has paused to speak with you before the next set of stairs."},{"i":4,"pts":[[-132.99486,64.542946]],"t":"Gori is catching his breath after the battle and motions you over to talk with him."}]}