{"n":"Instance: The Wedding Banquet","lv":0,"maps":["1879407790"],"steps":[{"i":1,"pts":[[53.174824,30.024824]],"t":"Merethien, the Master Foodmonger of Minas Tirith, has some questions for Merry and Pippin concerning what qualifies as a 'banquet' at their home, the …"},{"i":2,"pts":[[53.13697,30.089102]],"t":"Merethien wants to know if Merry and Pippin are satisfied that the wedding-feast she has helped to prepare can compare with the banquets they describe…"},{"i":4,"pts":[[53.053593,30.083487]],"t":"Beregond and his family sit at Pippin's table with a number of Gondorian nobles."},{"i":5,"pts":[[53.054863,30.048056]],"t":"Thrymm Red-beard has obtained a captive audience, and is regaling them with tales of his adventures."},{"i":7,"pts":[[53.060604,30.048065]],"t":"Prince Imrahil was given a message for you."},{"i":8,"pts":[[53.10197,30.150879]],"t":"Prince Imrahil told you a wine steward working at the wedding-feast wanted you to meet with him downstairs."},{"i":9,"pts":[[-55.88416,22.529472,"1879407790"]],"t":"The wine steward gave you some fine bottles of Gondor's finest to use as a peace offering with the 'rough sorts' gathering outside. You have been task…"},{"i":11,"pts":[[-55.890175,22.535986,"1879407790"],[-55.907333,22.542597,"1879407790"]],"t":"The Grey Company has gathered to celebrate the wedding of their chieftain, and to honour the great deeds done on his behalf."},{"i":12,"pts":[[53.09783,30.15949]],"t":"You should return to the wedding-feast, which will likely soon be winding down."},{"i":13,"pts":[[53.10197,30.150879]],"t":"The wine steward is being regaled with tales of Thrymm's heroics, and he wishes to speak with you."},{"i":14,"pts":[[53.01246,30.06745]],"t":"The wedding-feast continues into the night and you should speak with King Elessar before the festivities conclude."},{"i":15,"pts":[[53.063614,30.130732]],"t":"Prince Faramir of Ithilien is at the head table in Merethrond."},{"i":16,"pts":[[53.071854,30.130468]],"t":"Samwise Gamgee is at the head table in Merethrond."},{"i":18,"pts":[[53.01246,30.06745]],"t":"King Elessar wishes to speak with you."}]}