{"n":"Book 6, Chapter 9: Ancient Battlefield","lv":75,"maps":[],"steps":[{"i":1,"pts":[[-58.28488,-26.607723]],"t":"Cerdic is at the watch-post on the road into Parth Celebrant. Horn has given you a map of notable sites at the Battle of the Field of Celebrant to sho…"},{"i":2,"pts":[[-58.26359,-28.036678],[-58.32533,-28.779667],[-56.8912,-29.628622]],"t":"Cerdic has marked three locations in Parth Celebrant on your map: the crumbled base of a pillar, an arrow-riddled patch of ground, and the river-bank …"},{"i":3,"pts":[[-58.28488,-26.607723]],"t":"Cerdic is at the watch-post on the road as it enters Parth Celebrant from Eorlsmead. You have found a bronze-worked heirloom at one of the sites of th…"},{"i":4,"pts":[[-55.242107,-29.075956]],"t":"Edbrit is in the Rushgore at Aculf's Camp, south-east of Cerdic on the very edge of the swamp. While you were searching the battlefield of Parth Celeb…"}]}