{"n":"One Final Wager","lv":45,"maps":["1879443716"],"steps":[{"i":1,"pts":[[-22.789745,-43.121487,"1879443716"]],"t":"Cariad will be waiting for you outside of Tornhad, south of the river. You should meet up with him."},{"i":2,"pts":[[-22.797188,-43.121883,"1879443716"]],"t":"It seems Cariad has not escaped the sharp eyes of the Rangers. You should talk to Lagordal outside Tornhad."},{"i":3,"pts":[[-23.394335,-42.2257]],"t":"With Cariad captured, the next thing to do would be to notify Erlys. She can be found in the Cuan-lûth Refuge, to the north of Tornhad."}]}