{"n":"Wild Horses","lv":85,"maps":[],"steps":[{"i":1,"pts":[[-59.148865,-44.821766],[-59.124237,-44.811394],[-59.156307,-44.85395],[-59.217636,-44.88798],[-59.072605,-44.832596],[-59.140663,-44.87776],[-59.105244,-44.847363],[-59.184814,-44.850117]],"t":"The wild horses can be found at the base of the cliff south-west of Cliving. Gladsnel asked you to catch a wild horse and bring it back to Cliving."},{"i":2,"pts":[[-56.53832,-43.202915]],"t":"Gladsnel is in Cliving. Gladsnel will be pleased to hear that you caught a wild horse."}]}