{"n":"Sully the Stores","lv":73,"maps":[],"steps":[{"i":1,"pts":[[-11.02541,-88.00754],[-11.356973,-88.04186],[-11.505791,-88.08215],[-11.216093,-88.08748],[-11.453632,-88.22617],[-10.988281,-88.295334],[-10.9535055,-88.25052],[-9.815771,-88.955574],[-9.866806,-89.15381],[-9.902021,-88.96537]],"t":"The village of Cuvnerth lies to the south-east of Garrun's camp. Garrun asked you to enter the village of Cuvnerth and destroy the supplies they have …"},{"i":2,"pts":[[-11.948837,-87.47193]],"t":"Garrun's camp lies to the west of Cuvnerth. You should return to Garrun with news of your success."}]}