{"n":"Instance: The Legacy of Durin's Folk","lv":115,"maps":["1879358081"],"steps":[{"i":1,"pts":[[53.476093,14.01247,"1879358081"]],"t":"King Thorin III is standing before his throne in the Hall Under the Mountain. At King Thorin's request, you have come to attend a great feast and cele…"},{"i":3,"pts":[[53.46201,14.12956,"1879358081"]],"t":"Your seat can be found next to Dwalin at the leftmost end of the table. King Thorin has offered you a seat at his table, and you should now inspect it…"},{"i":4,"pts":[[53.476093,14.01247,"1879358081"]],"t":"King Thorin is standing beside his table in the Hall Under the Mountain. You have inspected the chair King Thorin chose for you, and you should now sp…"},{"i":5,"pts":[[53.28078,14.24998,"1879358081"]],"t":"The Stout-axes can be found somewhere among the celebrations in the Hall Under the Mountain. King Thorin III has asked you to find Spakorth, Dréri, an…"},{"i":6,"pts":[[53.469414,14.11751,"1879358081"],[53.251736,14.272968,"1879358081"]],"t":"Spakorth can be found among the revellers in the Hall Under the Mountain. You have found Spakorth, Dréri, and Náth and should now request that they jo…"},{"i":7,"pts":[[53.462128,14.131269,"1879358081"]],"t":"You have summoned the Stout-axes to the Feast of Durin's Folk, and you should now return to your seat at King Thorin's table."},{"i":8,"pts":[[53.48875,14.129169,"1879358081"]],"t":"Glóin can be found at King Thorin's table in the Hall Under the Mountain. You have returned to King Thorin's table, but just as you were about to take…"},{"i":9,"pts":[[53.680077,13.759453,"1879358081"]],"t":"Gimli, Dori, and Nori can be found somewhere in the Hall Under the Mountain. Glóin has asked that you find Gimli, Dori, and Nori and send them to join…"},{"i":10,"pts":[[53.493828,14.12916,"1879358081"],[53.69045,13.757988,"1879358081"]],"t":"Gimli, Dori, and Nori can be found on the upper level of the Hall Under the Mountain. You have found Gimli, Dori, and Nori and should now urge them to…"},{"i":11,"pts":[[53.476093,14.01247,"1879358081"]],"t":"King Thorin III can be found at his table in the Hall Under the Mountain. You have found all the missing dwarves and should now return to King Thorin …"},{"i":16,"pts":[[53.476093,14.01247,"1879358081"]],"t":"King Thorin III is standing beside his table in the Hall Under the Mountain. All of King Thorin's guests have arrived, and now the feast can begin. Yo…"}]}