{"n":"Instance: Into the Abyss","lv":109,"maps":["1879356000"],"steps":[{"i":1,"pts":[[50.576893,-2.0228612,"1879356000"]],"t":"Gimli can be found on the precipice within the abyss of Mordath. You descended into the abyss of Mordath and have come to a ledge within depths of Bar…"},{"i":3,"pts":[[50.576893,-2.0228612,"1879356000"]],"t":"Gimli is standing in the Chamber of the Watchers in the depths of Barad-dûr. You and Gimli have found a grisly trail of slain followers of the Order o…"},{"i":5,"pts":[[50.576893,-2.0228612,"1879356000"]],"t":"Gimli can be found in the Chamber of the Watchers in Barad-dûr. You have repelled the attacks of a glamour, one of the remnants of the Dark Lord himse…"}]}