{"n":"Tol Fennas - The Corsair Croup","lv":100,"maps":[],"steps":[{"i":1,"pts":[[-83.09893,-74.90659],[-83.1443,-74.912506],[-83.17703,-75.04541],[-83.08709,-75.11788],[-83.010925,-75.06889],[-82.824585,-74.821144],[-83.13562,-74.86299],[-83.19111,-75.10195],[-82.93338,-74.94219],[-82.975,-75.21029]],"t":"Sick Corsairs are at the Makham Hosh, the hunting camp on the west side of Tol Fennas. Glíreth asked you to defeat the sick Corsairs at the hunting ca…"},{"i":2,"pts":[[-71.339645,-75.144775]],"t":"Glíreth is in Dol Amroth. Glíreth will be pleased to hear the sick Corsairs have been cleansed."}]}