{"n":"The Impostor King","lv":105,"maps":[],"steps":[{"i":1,"pts":[[-6.3049316,-31.799892],[-6.070293,-32.180984],[-6.0852637,-32.203243],[-6.270068,-31.80329],[-5.7012987,-32.47883],[-5.7223043,-32.495575]],"t":"The cage-waggons can be found to the south-east of Ondoher's Folly. Faramir has asked you to dismantle the cage-waggons making for Ondoher's Folly and…"},{"i":2,"pts":[[-7.068027,-31.724384]],"t":"Artamir can be found to the south outside Ondoher's Folly in Dagorlad. You damaged the cage-waggons and learned much of the master of Ondoher's Folly,…"}]}