{"n":"Chapter 12.2: The Dead Forest","lv":150,"maps":[],"steps":[{"i":1,"pts":[[-70.57615,-36.277313]],"t":"The road into Imhûlar crosses the River Barûg north of Shonith."},{"i":2,"pts":[[-70.57795,-36.267246]],"t":"Sigileth stands just within the entrance to Imhûlar."},{"i":3,"pts":[[-70.568985,-36.28416]],"t":"Silirtas is just inside the entrance to Imhûlar."},{"i":5,"pts":[[-64.53688,-42.1433]],"t":"The leader of the Kintai at Vartúlin is named Thórvilon, and can be found in southern Imhûlar."},{"i":6,"pts":[[-64.53661,-42.155]],"t":"Thórvilon, leader of the Kintai at Vartúlin, is in southern Imhûlar."},{"i":7,"pts":[[-64.54293,-42.137966]],"t":"Silirtas stands by Thórvilon in Vartúlin."},{"i":8,"pts":[[-64.53661,-42.155]],"t":"Thórvilon, leader of the Kintai at Vartúlin is in southern Imhûlar."}]}