{"n":"Swarming the Nests","lv":76,"maps":[],"steps":[{"i":1,"pts":[[-50.667576,-41.721405],[-50.47369,-41.906532],[-50.463768,-41.73208],[-50.525047,-41.587578],[-50.365242,-41.47999],[-50.623447,-41.546513],[-50.19873,-41.640488],[-50.321552,-41.860184],[-50.75292,-41.36575]],"t":"The Stinging Bog is on the far side of the road from the Feldburg. You should destroy nests of the huge stinging marsh-flies in the Stinging Bog."},{"i":2,"pts":[[-51.989227,-42.459568]],"t":"Captain Agelmund is at Feldburg in the Wold. You should speak with Captain Agelmund."}]}