{"n":"The Way It Catches the Light, Part 1","lv":150,"maps":[],"steps":[{"i":1,"pts":[[-141.83266,-119.06177]],"t":"Investigate Sektakhâb for Khaltâg's wife's necklace. Sektakhâb is located west of Mekab-kuphâr in Khabârkhad."},{"i":3,"pts":[[-140.22997,-119.78517]],"t":"Return to Mekab-kuphâr to give Khaltâg his wife's necklace."},{"i":4,"pts":[[-141.13776,-122.35432]],"t":"Khaltâg has asked you to inform Pharida, his daughter, that her mother's necklace has been found. She can be found working in the Dûlkar, in Dil-irmíz…"}]}