{"n":"A Chill Draft","lv":55,"maps":[],"steps":[{"i":1,"pts":[[-105.57783,-6.428535]],"t":"Blown-out torches can be found near the south arch of the Twenty-first Hall. You should light the torches to stave off the chill draft."},{"i":2,"pts":[[-105.45055,-6.334443],[-105.644005,-6.271738],[-105.71369,-6.332783],[-105.50666,-6.2544823],[-105.64551,-6.2701464],[-105.508965,-6.256328],[-105.71869,-6.3362985],[-105.50621,-6.2575974]],"t":"Blown-out torches can be found near the south arch of the Twenty-first Hall. You should light the torches to stave off the chill draft."}]}