{"n":"Chapter 8.3: The Words in the Wards","lv":150,"maps":[],"steps":[{"i":1,"pts":[[-98.91473,-17.934834],[-98.664955,-17.604296],[-97.7382,-18.381933]],"t":"Corudan has asked you to speak with residents of the Upper Ward of Umbar Baharbêl about Azagath and the other leaders of the Kindred that fled with hi…"},{"i":2,"pts":[[-97.94371,-21.368114],[-98.10457,-20.796543]],"t":"Corudan has asked you to speak with residents of the Lower Ward of Umbar Baharbêl about Azagath and the other leaders of the Kindred that fled with hi…"},{"i":3,"pts":[[-97.949844,-20.210371]],"t":"Corudan has asked you to speak with residents of the Lower Ward of Umbar Baharbêl about Azagath and the other leaders of the Kindred that fled with hi…"},{"i":4,"pts":[[-100.40978,-20.034815]],"t":"A man in the Lower Ward told you he saw a well-dressed man in blue and silver walking along one of the north-south piers extending out into the waters…"},{"i":5,"pts":[[-100.40783,-20.075624]],"t":"Belondor stands atop one of the piers extending out into the waters of the Sail-haven."}]}