{"n":"Book 4, Chapter 2: The Missing Rider","lv":38,"maps":[],"steps":[{"i":1,"pts":[[-18.377666,-36.598083],[-18.04202,-35.584667]],"t":"The hoofprints were discovered far south of the road, and the sons of Elrond believe that the missing Rider might be hiding in the ruins of Minas Agor…"},{"i":2,"pts":[[-18.377607,-36.598164],[-18.04202,-35.584667]],"t":"The corpse of a black horse lies in the ruins of Minas Agor, located among the narrow channels of the South Trollshaws. You should remove the bridle f…"},{"i":3,"pts":[[-15.175156,-31.650175]],"t":"Elladan is at Thorenhad, located among the Bruinen Gorges, north of a bear-den. Elladan will be both pleased and troubled to see the bridle of the bla…"}]}