{"n":"Chapter 10: Forgotten Lineage","lv":50,"maps":[],"steps":[{"i":1,"pts":[[-6.149199,-28.54787]],"t":"Dithalion is by the forges in Rivendell. Hundi bid you to show your new weapon to Dithalion, an Elf of Rivendell who will be able to help you make use…"},{"i":2,"pts":[[-6.149199,-28.54787]],"t":"Dithalion is at the Forges of Rivendell."},{"i":3,"pts":[[-6.149199,-28.54787]],"t":"Dithalion is at the Forges of Rivendell. You have inscribed a tracery into your weapon and should now speak with Dithalion."}]}