{"n":"Pretty Parched Party-goers!","lv":0,"maps":[],"steps":[{"i":1,"pts":[[-51.34243,-24.3008],[-51.29033,-24.711395],[-51.283855,-24.654081],[-51.239803,-24.664951],[-51.23042,-24.70122],[-51.261814,-24.71079]],"t":"Jugs of spring wine can be found on the tables in the centre of the Festival Grounds. Arn Bulrush asked you to deliver jugs of spring wine to tables o…"},{"i":2,"pts":[[-51.187332,-24.875908],[-51.29033,-24.711395],[-51.283855,-24.654081],[-51.239803,-24.664951],[-51.23042,-24.70122],[-51.261814,-24.71079]],"t":"Jugs of spring wine can be found on the tables in the centre of the Festival Grounds. Arn Bulrush asked you to deliver jugs of spring wine to tables o…"},{"i":3,"pts":[[-51.67542,-24.903496],[-51.29033,-24.711395],[-51.283855,-24.654081],[-51.239803,-24.664951],[-51.23042,-24.70122],[-51.261814,-24.71079]],"t":"Jugs of spring wine can be found on the tables in the centre of the Festival Grounds. Arn Bulrush asked you to deliver jugs of spring wine to tables o…"},{"i":4,"pts":[[-51.700165,-24.653114]],"t":"Arn Bulrush is waiting to hear if your wine deliveries brought refreshment to the parched partygoers."}]}