{"n":"Chapter 6.1: The Road From Jax Phanâl","lv":147,"maps":[],"steps":[{"i":1,"pts":[[-114.40712,-14.397773]],"t":"The settlement of Jax Phanâl is to the east."},{"i":2,"pts":[[-114.421906,-14.371347]],"t":"Jâkin is in the settlement of Jax Phanâl, on the Cape of Umbar."},{"i":3,"pts":[[-114.40918,-14.407549],[-114.40918,-14.407549]],"t":"Driftwood has accompanied you to Jax Phanâl, on the Cape of Umbar."},{"i":4,"pts":[[-114.421906,-14.371347]],"t":"Jâkin is in the settlement of Jax Phanâl, on the Cape of Umbar."},{"i":5,"pts":[[-114.80892,-16.496826],[-115.003365,-16.643661],[-114.894936,-16.969667]],"t":"The Haradrim that were pushed out of Jax Phanâl have a camp to the south where they keep the things they stole.","kz":{"c":8}},{"i":6,"pts":[[-114.421906,-14.371347],[-114.80892,-16.496826],[-115.003365,-16.643661],[-114.894936,-16.969667]],"t":"You recovered the stolen books and should bring them back to Jâkin in Jax Phanâl."},{"i":7,"pts":[[-114.40918,-14.407549],[-114.40918,-14.407549]],"t":"Driftwood has accompanied you to Jax Phanâl, on the Cape of Umbar."},{"i":8,"pts":[[-114.48456,-14.738388]],"t":"Nauriel has made the crossing from the Shield Isles to the Cape of Umbar, and you should speak with her outside Jax Phanâl."}]}