{"n":"Other Prisoners","lv":45,"maps":["1879101640"],"steps":[{"i":1,"pts":[[55.06455,-64.91464,"1879101640"],[54.966446,-64.91515,"1879101640"]],"t":"The Elf-maiden and the goblin-prisoner are both in the dungeons of Goblin-town. Aeglas seems unconcerned that he is captured by the goblins of Goblin-…"},{"i":2,"pts":[[54.976055,-65.01672,"1879101640"]],"t":"Return to Aeglas within his cell in the Goblin-town prison. Oghûk seemed an untrusting sort and offered no information unless you helped him. Glorwen …"}]}