{"n":"Desolation on the Coast","lv":100,"maps":[],"steps":[{"i":1,"pts":[[-45.777107,-83.837204]],"t":"Ethillorn can be found to the south-west of Sarnhad in Lower Lebennin. Baraniel has asked you to search the sacked town of Ethillorn for any sign of s…"},{"i":2,"pts":[[-45.616367,-83.95787]],"t":"Ethillorn can be found to the south-west of Sarnhad in Lower Lebennin. You have searched near the entrance of Ethillorn, but have not yet found any su…"},{"i":3,"pts":[[-45.359257,-84.34992],[-45.886112,-84.2742],[-45.56871,-84.33233],[-45.500908,-84.13523],[-45.207012,-84.35281],[-45.462322,-84.412285],[-45.731552,-84.46956],[-45.966816,-84.4218]],"t":"Enslaved Gondorians can likely be found near the Corsair ships moored at Ethillorn. You have found one survivor in Ethillorn and he has begged your ai…"},{"i":4,"pts":[[-43.85992,-81.38378]],"t":"Baraniel can be found in Sarnhad in western Lower Lebennin. You have freed all the enslaved Gondorians you could, but not all were so fortunate. You s…"}]}