{"n":"Chapter 13.6: The Madness In His Eyes","lv":150,"maps":[],"steps":[{"i":1,"pts":[[-125.682144,66.31757]],"t":"Belondor wants to send some of his soldiers to fight alongside Sirgon at the front line to the north-east."},{"i":2,"pts":[[-125.66445,66.30941]],"t":"Elladan fights by Sirgon's side during the Dagor Carlanthir."},{"i":3,"pts":[[-125.670975,66.30767]],"t":"Sirgon has been grievously injured during the Dagor Carlanthir."},{"i":5,"pts":[[-125.54357,66.3426]],"t":"Corudan stands in the middle of the river during the Dagor Carlanthir."},{"i":7,"pts":[[-125.26005,66.74783]],"t":"Silirtas lies outside Utug-bûr during the Dagor Carlanthir."},{"i":8,"pts":[[-125.23145,66.73852]],"t":"Corudan stands outside Utug-bûr during the Dagor Carlanthir."}]}